jumblecsv/__init__.py
jumblecsv/main.py
jumblecsv-0.1.5.dist-info/METADATA
jumblecsv-0.1.5.dist-info/WHEEL
jumblecsv-0.1.5.dist-info/entry_points.txt
jumblecsv-0.1.5.dist-info/top_level.txt
jumblecsv-0.1.5.dist-info/RECORD
